.travis.yml
LICENSE
MANIFEST.in
README.rst
setup.cfg
setup.py
Mopidy_AlarmClock.egg-info/PKG-INFO
Mopidy_AlarmClock.egg-info/SOURCES.txt
Mopidy_AlarmClock.egg-info/dependency_links.txt
Mopidy_AlarmClock.egg-info/entry_points.txt
Mopidy_AlarmClock.egg-info/not-zip-safe
Mopidy_AlarmClock.egg-info/requires.txt
Mopidy_AlarmClock.egg-info/top_level.txt
mopidy_alarmclock/__init__.py
mopidy_alarmclock/alarm_manager.py
mopidy_alarmclock/backup-alarm.mp3
mopidy_alarmclock/ext.conf
mopidy_alarmclock/http.py
mopidy_alarmclock/static/bootstrap-theme.css
mopidy_alarmclock/static/bootstrap.css
mopidy_alarmclock/static/bootstrap.js
mopidy_alarmclock/static/clockpicker.css
mopidy_alarmclock/static/clockpicker.js
mopidy_alarmclock/static/jquery.js
mopidy_alarmclock/static/theme.css
mopidy_alarmclock/templates/base.html
mopidy_alarmclock/templates/index.html
tests/__init__.py
tests/test_alarm_manager.py
tests/test_extension.py
tests/test_http.py