Metadata-Version: 1.1
Name: Mopidy-AlarmClock
Version: 0.1.7
Summary: A Mopidy extension for using it as an alarm clock.
Home-page: https://github.com/DavisNT/mopidy-alarmclock
Author: Davis Mosenkovs
Author-email: python-apps@dm.id.lv
License: Apache License, Version 2.0
Platform: UNKNOWN
Classifier: Environment :: No Input/Output (Daemon)
Classifier: Intended Audience :: End Users/Desktop
Classifier: License :: OSI Approved :: Apache Software License
Classifier: Operating System :: OS Independent
Classifier: Programming Language :: Python :: 2
Classifier: Topic :: Multimedia :: Sound/Audio :: Players
